DevSqlite3/__init__.py
DevSqlite3/command.py
DevSqlite3/core.py
DevSqlite3/error.py
DevSqlite3/field.py
DevSqlite3-1.2.dist-info/LICENSE.txt
DevSqlite3-1.2.dist-info/METADATA
DevSqlite3-1.2.dist-info/WHEEL
DevSqlite3-1.2.dist-info/top_level.txt
DevSqlite3-1.2.dist-info/RECORD
