Metadata-Version: 2.1
Name: DevSqlite3
Version: 1.2
Summary: Sqlite3 helper
Home-page: https://github.com/omar-othmann/DevSqlite3
Author: Omar Othman
Author-email: ceunix@gmail.com
License: UNKNOWN
Platform: UNKNOWN
Classifier: Programming Language :: Python :: 2
Classifier: License :: OSI Approved :: MIT License
Classifier: Operating System :: OS Independent
Requires-Python: >=2
License-File: LICENSE.txt
